symmray/__init__.py
symmray/_version.py
symmray/abelian_common.py
symmray/common.py
symmray/fermionic_common.py
symmray/fermionic_local_operators.py
symmray/hamiltonians.py
symmray/index_common.py
symmray/interface.py
symmray/linalg.py
symmray/networks.py
symmray/symmetries.py
symmray/utils.py
symmray/utils_test.py
symmray/vector_common.py
symmray/flat/__init__.py
symmray/flat/flat_abelian_array.py
symmray/flat/flat_array_common.py
symmray/flat/flat_data_common.py
symmray/flat/flat_fermionic_array.py
symmray/flat/flat_index.py
symmray/flat/flat_vector.py
symmray/scipy/__init__.py
symmray/scipy/linalg.py
symmray/sparse/__init__.py
symmray/sparse/sparse_abelian_array.py
symmray/sparse/sparse_array_common.py
symmray/sparse/sparse_data_common.py
symmray/sparse/sparse_fermionic_array.py
symmray/sparse/sparse_index.py
symmray/sparse/sparse_vector.py
symmray-0.1.1.dist-info/METADATA
symmray-0.1.1.dist-info/WHEEL
symmray-0.1.1.dist-info/licenses/LICENSE
symmray-0.1.1.dist-info/RECORD
