Metadata-Version: 2.4
Name: symmray
Version: 0.1.1
Summary: A minimal block sparse symmetric and fermionic tensor python library
Project-URL: Documentation, https://symmray.readthedocs.io/
Project-URL: Repository, https://github.com/jcmgray/symmray/
Project-URL: Issues, https://github.com/jcmgray/symmray/issues
Project-URL: Changelog, https://github.com/jcmgray/symmray/releases
Author-email: Johnnie Gray <johnniemcgray@gmail.com>
License: Apache-2.0
License-File: LICENSE
Keywords: autoray,block,dmrg,fermions,mera,networks,peps,physics,quantum,sparse,symmetry,tebd,tensor,tensors
Classifier: Development Status :: 3 - Alpha
Classifier: License :: OSI Approved :: Apache Software License
Classifier: Programming Language :: Python :: 3
Classifier: Programming Language :: Python :: 3.10
Classifier: Programming Language :: Python :: 3.11
Classifier: Programming Language :: Python :: 3.12
Classifier: Programming Language :: Python :: 3.13
Requires-Python: >=3.10
Requires-Dist: autoray
Provides-Extra: docs
Requires-Dist: astroid<3; extra == 'docs'
Requires-Dist: furo; extra == 'docs'
Requires-Dist: ipython!=8.7.0; extra == 'docs'
Requires-Dist: myst-nb; extra == 'docs'
Requires-Dist: setuptools-scm; extra == 'docs'
Requires-Dist: sphinx-autoapi; extra == 'docs'
Requires-Dist: sphinx-copybutton; extra == 'docs'
Requires-Dist: sphinx>=2.0; extra == 'docs'
Provides-Extra: testing
Requires-Dist: cotengra; extra == 'testing'
Requires-Dist: coverage; extra == 'testing'
Requires-Dist: einops; extra == 'testing'
Requires-Dist: numpy; extra == 'testing'
Requires-Dist: pytest; extra == 'testing'
Requires-Dist: pytest-cov; extra == 'testing'
Requires-Dist: quimb; extra == 'testing'
